model_lifecycle/__init__.py
model_lifecycle/models.py
django_model_lifecycle-0.0.1.dist-info/LICENSE
django_model_lifecycle-0.0.1.dist-info/METADATA
django_model_lifecycle-0.0.1.dist-info/WHEEL
django_model_lifecycle-0.0.1.dist-info/top_level.txt
django_model_lifecycle-0.0.1.dist-info/RECORD
