Metadata-Version: 2.1
Name: django-model-lifecycle
Version: 0.0.1
Home-page: https://github.com/davidslusser/django-model-lifecycle
Author: David Slusser
Author-email: dbslusser@gmail.com
License: MIT
Platform: any
Requires-Python: >=3.8
License-File: LICENSE
Requires-Dist: Django
